MANIFEST.in
README.md
setup.py
tests.py
docs/Makefile
docs/api.rst
docs/conf.py
docs/index.rst
docs/installation.rst
docs/logo.png
docs/usage.rst
kt/__init__.py
kt/_binary.c
kt/_binary.pyx
kt/client.py
kt/constants.py
kt/embedded.py
kt/exceptions.py
kt/http.py
kt/models.py
kt.egg-info/PKG-INFO
kt.egg-info/SOURCES.txt
kt.egg-info/dependency_links.txt
kt.egg-info/top_level.txt
kt/scripts/kt-queue.lua
kt/scripts/kt.lua
kt/scripts/tt.lua