Metadata-Version: 1.0
Name: kt
Version: 0.9.4
Summary: Fast Python bindings for KyotoTycoon.
Home-page: UNKNOWN
Author: Charles Leifer
Author-email: UNKNOWN
License: UNKNOWN
Platform: UNKNOWN
